Metadata-Version: 2.1
Name: verysimplemodule-liedson
Version: 0.0.2
Summary: My first Python package
Author: liedson
Author-email: fabricoliedson@gamil.com
Keywords: python,math
Classifier: Development Status :: 3 - Alpha
Classifier: Intended Audience :: Education
Classifier: Programming Language :: Python :: 3
